chickenstats/__init__.py
chickenstats/api/__init__.py
chickenstats/api/api.py
chickenstats/chicken_nhl/__init__.py
chickenstats/chicken_nhl/_aggregation.py
chickenstats/chicken_nhl/_fixes.py
chickenstats/chicken_nhl/_helpers.py
chickenstats/chicken_nhl/_player_info.py
chickenstats/chicken_nhl/_team_info.py
chickenstats/chicken_nhl/_validation.py
chickenstats/chicken_nhl/_xg.py
chickenstats/chicken_nhl/info.py
chickenstats/chicken_nhl/scrape.py
chickenstats/chicken_nhl/score_adjustments/__init__.py
chickenstats/chicken_nhl/score_adjustments/score_adjustments.pkl
chickenstats/chicken_nhl/xg_models/__init__.py
chickenstats/chicken_nhl/xg_models/empty-against-0.1.1.json
chickenstats/chicken_nhl/xg_models/empty-for-0.1.1.json
chickenstats/chicken_nhl/xg_models/even-strength-0.1.1.json
chickenstats/chicken_nhl/xg_models/powerplay-0.1.1.json
chickenstats/chicken_nhl/xg_models/shorthanded-0.1.1.json
chickenstats/evolving_hockey/__init__.py
chickenstats/evolving_hockey/base.py
chickenstats/evolving_hockey/stats.py
chickenstats/evolving_hockey/validation.py
chickenstats/utilities/__init__.py
chickenstats/utilities/utilities.py
chickenstats/utilities/styles/chickenstats.mplstyle
chickenstats/utilities/styles/chickenstats_dark.mplstyle
chickenstats-1.7.9.26.dist-info/METADATA
chickenstats-1.7.9.26.dist-info/WHEEL
chickenstats-1.7.9.26.dist-info/licenses/LICENSE
chickenstats-1.7.9.26.dist-info/RECORD
