Metadata-Version: 2.4
Name: chickenstats
Version: 1.7.9.26
Summary: A Python package for scraping & analyzing sports statistics
Author-email: chickenandstats <chicken@chickenandstats.com>
Maintainer-email: chickenandstats <chicken@chickenandstats.com>
License-Expression: GPL-3.0-only
License-File: LICENSE
Classifier: Development Status :: 5 - Production/Stable
Classifier: Intended Audience :: Developers
Classifier: License :: OSI Approved :: GNU General Public License v3 (GPLv3)
Classifier: Programming Language :: Python :: 3
Classifier: Programming Language :: Python :: 3.10
Classifier: Programming Language :: Python :: 3.11
Classifier: Programming Language :: Python :: 3.12
Classifier: Programming Language :: Python :: 3.13
Classifier: Topic :: Software Development :: Libraries
Requires-Python: >=3.10
Requires-Dist: beautifulsoup4>=4.12.3
Requires-Dist: chickenstats-api>=0.0.1
Requires-Dist: geopandas>=1.0.1
Requires-Dist: llvmlite>=0.44.0
Requires-Dist: lxml>=5.3.0
Requires-Dist: matplotlib>=3.9.2
Requires-Dist: numba>=0.61.0
Requires-Dist: numpy>=2.1
Requires-Dist: pandas>=2.2.2
Requires-Dist: pandera>=0.20.4
Requires-Dist: polars>=1.22.0
Requires-Dist: pydantic>=2.9.0
Requires-Dist: python-dotenv>=1.0.1
Requires-Dist: requests>=2.32.3
Requires-Dist: rich>=13.8.0
Requires-Dist: scikit-learn<1.8.0
Requires-Dist: shapely>=2.0.6
Requires-Dist: unidecode>=1.3.8
Requires-Dist: xgboost>=2.1.4
Requires-Dist: zensical>=0.0.10
Provides-Extra: mlflow
Requires-Dist: mlflow>=2.16.0; extra == 'mlflow'
Requires-Dist: optuna>=4.0.0; extra == 'mlflow'
Requires-Dist: shap>=0.46.0; extra == 'mlflow'
Requires-Dist: yellowbrick>=1.5; extra == 'mlflow'
Provides-Extra: plotting
Requires-Dist: bokeh>=3.6.3; extra == 'plotting'
Requires-Dist: hockey-rink>=1.0.3; extra == 'plotting'
Requires-Dist: networkx>=3.4.2; extra == 'plotting'
Requires-Dist: plotly>=6.0.0; extra == 'plotting'
Requires-Dist: seaborn>=0.13.2; extra == 'plotting'
